Activiti5XYonghuZhinan/README.md
Activiti5XYonghuZhinan/__init__.py
Activiti5XYonghuZhinan/__main__.py
Activiti5XYonghuZhinan/file.epub
Activiti5XYonghuZhinan/index.html
Activiti5XYonghuZhinan/css/__init__.py
Activiti5XYonghuZhinan/css/annotations.css
Activiti5XYonghuZhinan/css/main.css
Activiti5XYonghuZhinan/css/normalize.css
Activiti5XYonghuZhinan/css/popup.css
Activiti5XYonghuZhinan/font/__init__.py
Activiti5XYonghuZhinan/font/fontello.eot
Activiti5XYonghuZhinan/font/fontello.svg
Activiti5XYonghuZhinan/font/fontello.ttf
Activiti5XYonghuZhinan/font/fontello.woff
Activiti5XYonghuZhinan/img/__init__.py
Activiti5XYonghuZhinan/img/annotator-glyph-sprite.png
Activiti5XYonghuZhinan/img/annotator-icon-sprite.png
Activiti5XYonghuZhinan/img/apple-touch-icon.png
Activiti5XYonghuZhinan/img/cancelfullscreen.png
Activiti5XYonghuZhinan/img/close.png
Activiti5XYonghuZhinan/img/fullscreen.png
Activiti5XYonghuZhinan/img/loader.gif
Activiti5XYonghuZhinan/img/menu-icon.png
Activiti5XYonghuZhinan/img/save.png
Activiti5XYonghuZhinan/img/saved.png
Activiti5XYonghuZhinan/img/settings-s.png
Activiti5XYonghuZhinan/img/settings.png
Activiti5XYonghuZhinan/img/star.png
Activiti5XYonghuZhinan/js/__init__.py
Activiti5XYonghuZhinan/js/epub.js
Activiti5XYonghuZhinan/js/epub.min.js
Activiti5XYonghuZhinan/js/epub.min.map
Activiti5XYonghuZhinan/js/hooks.min.js
Activiti5XYonghuZhinan/js/hooks.min.map
Activiti5XYonghuZhinan/js/reader.js
Activiti5XYonghuZhinan/js/reader.js.map
Activiti5XYonghuZhinan/js/reader.min.js
Activiti5XYonghuZhinan/js/reader.min.map
Activiti5XYonghuZhinan/js/hooks/__init__.py
Activiti5XYonghuZhinan/js/hooks/extensions/__init__.py
Activiti5XYonghuZhinan/js/hooks/extensions/highlight.js
Activiti5XYonghuZhinan/js/libs/__init__.py
Activiti5XYonghuZhinan/js/libs/jquery.min.js
Activiti5XYonghuZhinan/js/libs/localforage.min.js
Activiti5XYonghuZhinan/js/libs/screenfull.js
Activiti5XYonghuZhinan/js/libs/screenfull.min.js
Activiti5XYonghuZhinan/js/libs/zip.min.js
activiti_5_x_yonghu_zhinan-2024.2.29.0.dist-info/METADATA
activiti_5_x_yonghu_zhinan-2024.2.29.0.dist-info/WHEEL
activiti_5_x_yonghu_zhinan-2024.2.29.0.dist-info/entry_points.txt
activiti_5_x_yonghu_zhinan-2024.2.29.0.dist-info/top_level.txt
activiti_5_x_yonghu_zhinan-2024.2.29.0.dist-info/RECORD
